hack4u/__init__.py
hack4u/courses.py
hack4u/utils.py
H4ck4u-7.7.7.dist-info/METADATA
H4ck4u-7.7.7.dist-info/WHEEL
H4ck4u-7.7.7.dist-info/top_level.txt
H4ck4u-7.7.7.dist-info/RECORD
