Metadata-Version: 2.1
Name: H4ck4u
Version: 7.7.7
Summary: Una biblioteca para consultar cursos de hack4u.
Home-page: https://hack4u.io
Author: Almandev
